{
    "version": "1.6.7",
    "description": "A note taking and to-do application with synchronization capabilities",
    "homepage": "https://joplinapp.org",
    "license": "MIT",
    "url": "https://github.com/laurent22/joplin/releases/download/v1.6.7/JoplinPortable.exe",
    "hash": "b38f46b86d92feaf9e1516ed573355cd09bfccd37791b5d5eca878fb76824bfb",
    "bin": "JoplinPortable.exe",
    "shortcuts": [
        [
            "JoplinPortable.exe",
            "JoplinPortable"
        ]
    ],
    "persist": "JoplinProfile",
    "checkver": {
        "github": "https://github.com/laurent22/joplin"
    },
    "autoupdate": {
        "url": "https://github.com/laurent22/joplin/releases/download/v$version/JoplinPortable.exe"
    }
}
